{
    "last_updated": "2026-06-22T00:05:44.991832",
    "prediction_for_date": "2026-06-23",
    "tomorrow_predictions": {
        "S&P 500": 0.0054695041328167455,
        "Nasdaq": 0.0037951549647693966,
        "Gold": -0.0058538339059330214,
        "SCB": -0.0028043600029560274,
        "TQM": 0.00042955397348289645,
        "IVV": 0.005470154650701512,
        "Google": 0.002528399563756097,
        "NVDA": 0.007697361500682672,
        "AMD": 0.018615291379420158,
        "TSM": 0.03917858074820569,
        "SMH": 0.031011748185288675,
        "MU": 0.02797785393578179,
        "WDC": 0.03473520782734121,
        "TSLA": 0.0016974436278892131,
        "RKLB": -0.018769563180181217,
        "Bitcoin": -0.0062479814684700315
    },
    "tomorrow_details": {
        "S&P 500": {
            "predicted_pct": 0.0054695041328167455,
            "predicted_dir": "Up",
            "rf_pct": 0.00877015408590037,
            "arima_pct": -0.0007128657414433912,
            "news_pct": 0.006745619047619047,
            "news_info": {
                "direction": "Up",
                "article_count": 2,
                "avg_credibility": 94.5,
                "sentiment_raw": 0.3373
            },
            "weights": {
                "rf": 0.357,
                "arima": 0.268,
                "news": 0.375
            }
        },
        "Nasdaq": {
            "predicted_pct": 0.0037951549647693966,
            "predicted_dir": "Up",
            "rf_pct": 0.010651157293765154,
            "arima_pct": -0.000630671019039316,
            "news_pct": 0.002061000000000001,
            "news_info": {
                "direction": "Up",
                "article_count": 2,
                "avg_credibility": 95.0,
                "sentiment_raw": 0.1031
            },
            "weights": {
                "rf": 0.294,
                "arima": 0.294,
                "news": 0.412
            }
        },
        "Gold": {
            "predicted_pct": -0.0058538339059330214,
            "predicted_dir": "Down",
            "rf_pct": -0.012982682059456683,
            "arima_pct": 0.0016230334971663288,
            "news_pct": -0.0006753333333333328,
            "news_info": {
                "direction": "Down",
                "article_count": 3,
                "avg_credibility": 95.0,
                "sentiment_raw": -0.0338
            },
            "weights": {
                "rf": 0.471,
                "arima": 0.269,
                "news": 0.26
            }
        },
        "SCB": {
            "predicted_pct": -0.0028043600029560274,
            "predicted_dir": "Down",
            "rf_pct": -0.004091853853261808,
            "arima_pct": -0.0017324606417344697,
            "news_pct": 0.0,
            "news_info": {
                "direction": "Neutral",
                "article_count": 0,
                "avg_credibility": null,
                "sentiment_raw": null
            },
            "weights": {
                "rf": 0.353,
                "arima": 0.424,
                "news": 0.223
            }
        },
        "TQM": {
            "predicted_pct": 0.00042955397348289645,
            "predicted_dir": "Up",
            "rf_pct": 0.00011657886311998489,
            "arima_pct": 0.0012127861024621622,
            "news_pct": 0.0,
            "news_info": {
                "direction": "Neutral",
                "article_count": 0,
                "avg_credibility": null,
                "sentiment_raw": null
            },
            "weights": {
                "rf": 0.493,
                "arima": 0.197,
                "news": 0.31
            }
        },
        "IVV": {
            "predicted_pct": 0.005470154650701512,
            "predicted_dir": "Up",
            "rf_pct": 0.008001299060506967,
            "arima_pct": -0.000864130598202497,
            "news_pct": 0.0,
            "news_info": {
                "direction": "Neutral",
                "article_count": 0,
                "avg_credibility": null,
                "sentiment_raw": null
            },
            "weights": {
                "rf": 0.493,
                "arima": 0.197,
                "news": 0.31
            }
        },
        "Google": {
            "predicted_pct": 0.002528399563756097,
            "predicted_dir": "Up",
            "rf_pct": 0.009786825546529593,
            "arima_pct": -0.00039876516885612654,
            "news_pct": -0.0068000000000000005,
            "news_info": {
                "direction": "Down",
                "article_count": 1,
                "avg_credibility": 95.0,
                "sentiment_raw": -0.34
            },
            "weights": {
                "rf": 0.513,
                "arima": 0.128,
                "news": 0.359
            }
        },
        "NVDA": {
            "predicted_pct": 0.007697361500682672,
            "predicted_dir": "Up",
            "rf_pct": 0.01979777212006163,
            "arima_pct": -0.003207809901223402,
            "news_pct": -0.011703,
            "news_info": {
                "direction": "Down",
                "article_count": 2,
                "avg_credibility": 95.0,
                "sentiment_raw": -0.5851
            },
            "weights": {
                "rf": 0.556,
                "arima": 0.222,
                "news": 0.222
            }
        },
        "AMD": {
            "predicted_pct": 0.018615291379420158,
            "predicted_dir": "Up",
            "rf_pct": 0.03680163746080509,
            "arima_pct": 0.003479309078140129,
            "news_pct": 0.0,
            "news_info": {
                "direction": "Neutral",
                "article_count": 0,
                "avg_credibility": null,
                "sentiment_raw": null
            },
            "weights": {
                "rf": 0.392,
                "arima": 0.471,
                "news": 0.137
            }
        },
        "TSM": {
            "predicted_pct": 0.03917858074820569,
            "predicted_dir": "Up",
            "rf_pct": 0.04766207461724294,
            "arima_pct": -0.0031486386622035854,
            "news_pct": 0.0,
            "news_info": {
                "direction": "Neutral",
                "article_count": 1,
                "avg_credibility": 94.0,
                "sentiment_raw": 0.0
            },
            "weights": {
                "rf": 0.469,
                "arima": 0.094,
                "news": 0.438
            }
        },
        "SMH": {
            "predicted_pct": 0.031011748185288675,
            "predicted_dir": "Up",
            "rf_pct": 0.04346507836244,
            "arima_pct": -0.0001531846945874823,
            "news_pct": 0.0,
            "news_info": {
                "direction": "Neutral",
                "article_count": 0,
                "avg_credibility": null,
                "sentiment_raw": null
            },
            "weights": {
                "rf": 0.493,
                "arima": 0.197,
                "news": 0.31
            }
        },
        "MU": {
            "predicted_pct": 0.02797785393578179,
            "predicted_dir": "Up",
            "rf_pct": 0.062414587226004944,
            "arima_pct": 0.012700343668632062,
            "news_pct": 0.0051939130434782614,
            "news_info": {
                "direction": "Up",
                "article_count": 3,
                "avg_credibility": 92.0,
                "sentiment_raw": 0.2597
            },
            "weights": {
                "rf": 0.352,
                "arima": 0.352,
                "news": 0.296
            }
        },
        "WDC": {
            "predicted_pct": 0.03473520782734121,
            "predicted_dir": "Up",
            "rf_pct": 0.052435187943681925,
            "arima_pct": 0.017035227711000484,
            "news_pct": 0.0,
            "news_info": {
                "direction": "Neutral",
                "article_count": 1,
                "avg_credibility": 95.0,
                "sentiment_raw": 0.0
            },
            "weights": {
                "rf": 0.387,
                "arima": 0.387,
                "news": 0.226
            }
        },
        "TSLA": {
            "predicted_pct": 0.0016974436278892131,
            "predicted_dir": "Up",
            "rf_pct": 0.0026751790835791277,
            "arima_pct": 0.0007197081721992986,
            "news_pct": 0.0,
            "news_info": {
                "direction": "Neutral",
                "article_count": 0,
                "avg_credibility": null,
                "sentiment_raw": null
            },
            "weights": {
                "rf": 0.37,
                "arima": 0.37,
                "news": 0.259
            }
        },
        "RKLB": {
            "predicted_pct": -0.018769563180181217,
            "predicted_dir": "Down",
            "rf_pct": -0.013793425859576552,
            "arima_pct": -0.02374570050078588,
            "news_pct": 0.0,
            "news_info": {
                "direction": "Neutral",
                "article_count": 1,
                "avg_credibility": 94.0,
                "sentiment_raw": 0.0
            },
            "weights": {
                "rf": 0.38,
                "arima": 0.38,
                "news": 0.24
            }
        },
        "Bitcoin": {
            "predicted_pct": -0.0062479814684700315,
            "predicted_dir": "Down",
            "rf_pct": -0.010228150309403852,
            "arima_pct": -0.000950054024794606,
            "news_pct": 0.0,
            "news_info": {
                "direction": "Neutral",
                "article_count": 1,
                "avg_credibility": 92.0,
                "sentiment_raw": 0.0
            },
            "weights": {
                "rf": 0.394,
                "arima": 0.296,
                "news": 0.31
            }
        }
    },
    "model_weights": {
        "S&P 500": {
            "rf": 0.357,
            "arima": 0.268,
            "news": 0.375,
            "rf_accuracy": 60.0,
            "arima_accuracy": 40.0,
            "news_accuracy": 66.7,
            "samples": 5
        },
        "Nasdaq": {
            "rf": 0.294,
            "arima": 0.294,
            "news": 0.412,
            "rf_accuracy": 40.0,
            "arima_accuracy": 40.0,
            "news_accuracy": 66.7,
            "samples": 5
        },
        "Gold": {
            "rf": 0.471,
            "arima": 0.269,
            "news": 0.26,
            "rf_accuracy": 85.7,
            "arima_accuracy": 42.9,
            "news_accuracy": 40.0,
            "samples": 7
        },
        "SCB": {
            "rf": 0.353,
            "arima": 0.424,
            "news": 0.223,
            "rf_accuracy": 80.0,
            "arima_accuracy": 100.0,
            "news_accuracy": null,
            "samples": 5
        },
        "TQM": {
            "rf": 0.493,
            "arima": 0.197,
            "news": 0.31,
            "rf_accuracy": 80.0,
            "arima_accuracy": 20.0,
            "news_accuracy": null,
            "samples": 5
        },
        "IVV": {
            "rf": 0.493,
            "arima": 0.197,
            "news": 0.31,
            "rf_accuracy": 80.0,
            "arima_accuracy": 20.0,
            "news_accuracy": null,
            "samples": 5
        },
        "Google": {
            "rf": 0.513,
            "arima": 0.128,
            "news": 0.359,
            "rf_accuracy": 60.0,
            "arima_accuracy": 0.0,
            "news_accuracy": 33.3,
            "samples": 5
        },
        "NVDA": {
            "rf": 0.556,
            "arima": 0.222,
            "news": 0.222,
            "rf_accuracy": 80.0,
            "arima_accuracy": 20.0,
            "news_accuracy": 20.0,
            "samples": 5
        },
        "AMD": {
            "rf": 0.392,
            "arima": 0.471,
            "news": 0.137,
            "rf_accuracy": 80.0,
            "arima_accuracy": 100.0,
            "news_accuracy": 0.0,
            "samples": 5
        },
        "TSM": {
            "rf": 0.469,
            "arima": 0.094,
            "news": 0.438,
            "rf_accuracy": 80.0,
            "arima_accuracy": 0.0,
            "news_accuracy": 100.0,
            "samples": 5
        },
        "SMH": {
            "rf": 0.493,
            "arima": 0.197,
            "news": 0.31,
            "rf_accuracy": 80.0,
            "arima_accuracy": 20.0,
            "news_accuracy": null,
            "samples": 5
        },
        "MU": {
            "rf": 0.352,
            "arima": 0.352,
            "news": 0.296,
            "rf_accuracy": 80.0,
            "arima_accuracy": 80.0,
            "news_accuracy": 66.7,
            "samples": 5
        },
        "WDC": {
            "rf": 0.387,
            "arima": 0.387,
            "news": 0.226,
            "rf_accuracy": 100.0,
            "arima_accuracy": 100.0,
            "news_accuracy": 50.0,
            "samples": 5
        },
        "TSLA": {
            "rf": 0.37,
            "arima": 0.37,
            "news": 0.259,
            "rf_accuracy": 80.0,
            "arima_accuracy": 80.0,
            "news_accuracy": 50.0,
            "samples": 5
        },
        "RKLB": {
            "rf": 0.38,
            "arima": 0.38,
            "news": 0.24,
            "rf_accuracy": 80.0,
            "arima_accuracy": 80.0,
            "news_accuracy": null,
            "samples": 5
        },
        "Bitcoin": {
            "rf": 0.394,
            "arima": 0.296,
            "news": 0.31,
            "rf_accuracy": 60.0,
            "arima_accuracy": 40.0,
            "news_accuracy": null,
            "samples": 5
        }
    },
    "evaluation": {
        "prediction_was_for": "2026-06-22",
        "made_on": "2026-06-21",
        "results": {
            "S&P 500": {
                "predicted_pct": 0.005632674946580353,
                "predicted_dir": "Up",
                "actual_pct": 0.010846212235623454,
                "actual_dir": "Up",
                "correct": true
            },
            "Nasdaq": {
                "predicted_pct": -0.0004224087844745593,
                "predicted_dir": "Down",
                "actual_pct": 0.01907140160428249,
                "actual_dir": "Up",
                "correct": false
            },
            "Gold": {
                "predicted_pct": -0.0044121763760536364,
                "predicted_dir": "Down",
                "actual_pct": -0.016547880194064078,
                "actual_dir": "Down",
                "correct": true
            },
            "SCB": {
                "predicted_pct": -0.0026047288392455187,
                "predicted_dir": "Down",
                "actual_pct": -0.007042253521126761,
                "actual_dir": "Down",
                "correct": true
            },
            "TQM": {
                "predicted_pct": -0.00021947962551625714,
                "predicted_dir": "Down",
                "actual_pct": 0.0,
                "actual_dir": "Down",
                "correct": true
            },
            "IVV": {
                "predicted_pct": 0.004803340744623397,
                "predicted_dir": "Up",
                "actual_pct": 0.010099514075951173,
                "actual_dir": "Up",
                "correct": true
            },
            "Google": {
                "predicted_pct": 0.0072445002019105136,
                "predicted_dir": "Up",
                "actual_pct": 0.01165504861261585,
                "actual_dir": "Up",
                "correct": true
            },
            "NVDA": {
                "predicted_pct": 0.0061711845370091105,
                "predicted_dir": "Up",
                "actual_pct": 0.029513846689763496,
                "actual_dir": "Up",
                "correct": true
            },
            "AMD": {
                "predicted_pct": 0.018293553084902495,
                "predicted_dir": "Up",
                "actual_pct": 0.04856777941973724,
                "actual_dir": "Up",
                "correct": true
            },
            "TSM": {
                "predicted_pct": 0.037499931190826806,
                "predicted_dir": "Up",
                "actual_pct": 0.06935092362371299,
                "actual_dir": "Up",
                "correct": true
            },
            "SMH": {
                "predicted_pct": 0.02892565670568774,
                "predicted_dir": "Up",
                "actual_pct": 0.05755090127049227,
                "actual_dir": "Up",
                "correct": true
            },
            "MU": {
                "predicted_pct": 0.02772239891035497,
                "predicted_dir": "Up",
                "actual_pct": 0.08704076335870717,
                "actual_dir": "Up",
                "correct": true
            },
            "WDC": {
                "predicted_pct": 0.034735207821951566,
                "predicted_dir": "Up",
                "actual_pct": 0.0478844808562012,
                "actual_dir": "Up",
                "correct": true
            },
            "TSLA": {
                "predicted_pct": 0.0016974436278892131,
                "predicted_dir": "Up",
                "actual_pct": 0.010368800900483349,
                "actual_dir": "Up",
                "correct": true
            },
            "RKLB": {
                "predicted_pct": -0.018769563180181217,
                "predicted_dir": "Down",
                "actual_pct": -0.006853171607320064,
                "actual_dir": "Down",
                "correct": true
            },
            "Bitcoin": {
                "predicted_pct": 0.0009949670538931996,
                "predicted_dir": "Up",
                "actual_pct": -0.013444280960273468,
                "actual_dir": "Down",
                "correct": false
            }
        }
    },
    "stats": {
        "overall_accuracy_pct": 77.9,
        "total_evaluated": 5,
        "per_symbol": {
            "S&P 500": {
                "total": 5,
                "correct": 3,
                "accuracy_pct": 60.0
            },
            "Nasdaq": {
                "total": 5,
                "correct": 2,
                "accuracy_pct": 40.0
            },
            "Gold": {
                "total": 7,
                "correct": 6,
                "accuracy_pct": 85.7
            },
            "SCB": {
                "total": 6,
                "correct": 5,
                "accuracy_pct": 83.3
            },
            "TQM": {
                "total": 6,
                "correct": 4,
                "accuracy_pct": 66.7
            },
            "IVV": {
                "total": 6,
                "correct": 5,
                "accuracy_pct": 83.3
            },
            "Google": {
                "total": 6,
                "correct": 4,
                "accuracy_pct": 66.7
            },
            "NVDA": {
                "total": 6,
                "correct": 5,
                "accuracy_pct": 83.3
            },
            "AMD": {
                "total": 6,
                "correct": 5,
                "accuracy_pct": 83.3
            },
            "TSM": {
                "total": 6,
                "correct": 5,
                "accuracy_pct": 83.3
            },
            "SMH": {
                "total": 6,
                "correct": 5,
                "accuracy_pct": 83.3
            },
            "MU": {
                "total": 6,
                "correct": 6,
                "accuracy_pct": 100.0
            },
            "WDC": {
                "total": 6,
                "correct": 5,
                "accuracy_pct": 83.3
            },
            "TSLA": {
                "total": 6,
                "correct": 5,
                "accuracy_pct": 83.3
            },
            "RKLB": {
                "total": 6,
                "correct": 5,
                "accuracy_pct": 83.3
            },
            "Bitcoin": {
                "total": 6,
                "correct": 4,
                "accuracy_pct": 66.7
            }
        },
        "all_correct_streak": 0,
        "recent_history": [
            {
                "for_date": "2026-06-16",
                "made_on": "unknown",
                "symbols": {
                    "S&P 500": {
                        "predicted_dir": "Up",
                        "predicted_pct": 0.006398034018782682,
                        "actual_dir": "Up",
                        "actual_pct": 0.016528391294663537,
                        "correct": true
                    },
                    "Nasdaq": {
                        "predicted_dir": "Up",
                        "predicted_pct": 0.011508299889526256,
                        "actual_dir": "Up",
                        "actual_pct": 0.030712135703985625,
                        "correct": true
                    },
                    "Gold": {
                        "predicted_dir": "Up",
                        "predicted_pct": 0.008097291752071158,
                        "actual_dir": "Up",
                        "actual_pct": 0.029252622701660735,
                        "correct": true
                    }
                }
            },
            {
                "for_date": "2026-06-17",
                "made_on": "2026-06-16",
                "symbols": {
                    "S&P 500": {
                        "predicted_dir": "Up",
                        "predicted_pct": 0.006398034018782682,
                        "actual_dir": "Down",
                        "actual_pct": -0.005684179609759717,
                        "correct": false
                    },
                    "Nasdaq": {
                        "predicted_dir": "Up",
                        "predicted_pct": 0.011508299889526256,
                        "actual_dir": "Down",
                        "actual_pct": -0.011527372248214908,
                        "correct": false
                    },
                    "Gold": {
                        "predicted_dir": "Up",
                        "predicted_pct": 0.008552244765861186,
                        "actual_dir": "Up",
                        "actual_pct": 0.0075323700684496305,
                        "correct": true
                    },
                    "SCB": {
                        "predicted_dir": null,
                        "predicted_pct": null,
                        "actual_dir": "Down",
                        "actual_pct": null,
                        "correct": true
                    },
                    "TQM": {
                        "predicted_dir": null,
                        "predicted_pct": null,
                        "actual_dir": "Down",
                        "actual_pct": -0.007352969019469962,
                        "correct": true
                    },
                    "IVV": {
                        "predicted_dir": null,
                        "predicted_pct": null,
                        "actual_dir": "Down",
                        "actual_pct": -0.00573803921517994,
                        "correct": true
                    },
                    "Google": {
                        "predicted_dir": null,
                        "predicted_pct": null,
                        "actual_dir": "Up",
                        "actual_pct": 0.010559073594251806,
                        "correct": false
                    },
                    "NVDA": {
                        "predicted_dir": null,
                        "predicted_pct": null,
                        "actual_dir": "Down",
                        "actual_pct": -0.023723197733726838,
                        "correct": true
                    },
                    "AMD": {
                        "predicted_dir": null,
                        "predicted_pct": null,
                        "actual_dir": "Down",
                        "actual_pct": -0.0730365831733641,
                        "correct": true
                    },
                    "TSM": {
                        "predicted_dir": null,
                        "predicted_pct": null,
                        "actual_dir": "Down",
                        "actual_pct": -0.03527414485617364,
                        "correct": true
                    },
                    "SMH": {
                        "predicted_dir": null,
                        "predicted_pct": null,
                        "actual_dir": "Down",
                        "actual_pct": -0.048060542048046016,
                        "correct": true
                    },
                    "MU": {
                        "predicted_dir": null,
                        "predicted_pct": null,
                        "actual_dir": "Down",
                        "actual_pct": -0.06179282996369048,
                        "correct": true
                    },
                    "WDC": {
                        "predicted_dir": null,
                        "predicted_pct": null,
                        "actual_dir": "Up",
                        "actual_pct": 0.042155657059262365,
                        "correct": false
                    },
                    "TSLA": {
                        "predicted_dir": null,
                        "predicted_pct": null,
                        "actual_dir": "Down",
                        "actual_pct": -0.015784969793794987,
                        "correct": true
                    },
                    "RKLB": {
                        "predicted_dir": null,
                        "predicted_pct": null,
                        "actual_dir": "Down",
                        "actual_pct": -0.04228835465978976,
                        "correct": true
                    },
                    "Bitcoin": {
                        "predicted_dir": null,
                        "predicted_pct": null,
                        "actual_dir": "Down",
                        "actual_pct": -0.007625995632792524,
                        "correct": true
                    }
                }
            },
            {
                "for_date": "2026-06-18",
                "made_on": "2026-06-17",
                "symbols": {
                    "S&P 500": {
                        "predicted_dir": "Up",
                        "predicted_pct": 0.000633521686808324,
                        "actual_dir": "Down",
                        "actual_pct": -0.01214828210822879,
                        "correct": false
                    },
                    "Nasdaq": {
                        "predicted_dir": "Down",
                        "predicted_pct": -0.0015536060779295284,
                        "actual_dir": "Down",
                        "actual_pct": -0.013447036088066024,
                        "correct": true
                    },
                    "Gold": {
                        "predicted_dir": "Up",
                        "predicted_pct": 0.0018675438521214614,
                        "actual_dir": "Down",
                        "actual_pct": -0.007688888092167443,
                        "correct": false
                    },
                    "SCB": {
                        "predicted_dir": "Up",
                        "predicted_pct": 0.0032855810253363434,
                        "actual_dir": "Down",
                        "actual_pct": -0.0035087719298245615,
                        "correct": false
                    },
                    "TQM": {
                        "predicted_dir": "Up",
                        "predicted_pct": 0.0009903363979029893,
                        "actual_dir": "Down",
                        "actual_pct": 0.0,
                        "correct": false
                    },
                    "IVV": {
                        "predicted_dir": "Down",
                        "predicted_pct": -0.0007478709173683368,
                        "actual_dir": "Down",
                        "actual_pct": -0.012499866081559414,
                        "correct": true
                    },
                    "Google": {
                        "predicted_dir": "Down",
                        "predicted_pct": -0.0001682792470132288,
                        "actual_dir": "Down",
                        "actual_pct": -0.025344920174355325,
                        "correct": true
                    },
                    "NVDA": {
                        "predicted_dir": "Down",
                        "predicted_pct": -0.00997809209672805,
                        "actual_dir": "Down",
                        "actual_pct": -0.01330702336865737,
                        "correct": true
                    },
                    "AMD": {
                        "predicted_dir": "Down",
                        "predicted_pct": -0.01448943062119393,
                        "actual_dir": "Up",
                        "actual_pct": 0.010230778916215415,
                        "correct": false
                    },
                    "TSM": {
                        "predicted_dir": "Down",
                        "predicted_pct": -0.01298941379534824,
                        "actual_dir": "Up",
                        "actual_pct": 0.014841621124646211,
                        "correct": false
                    },
                    "SMH": {
                        "predicted_dir": "Down",
                        "predicted_pct": -0.013519106338264003,
                        "actual_dir": "Up",
                        "actual_pct": 0.012938264128449676,
                        "correct": false
                    },
                    "MU": {
                        "predicted_dir": "Up",
                        "predicted_pct": 0.0009506809071694218,
                        "actual_dir": "Up",
                        "actual_pct": 0.02197375624636304,
                        "correct": true
                    },
                    "WDC": {
                        "predicted_dir": "Up",
                        "predicted_pct": 0.028485413719009253,
                        "actual_dir": "Up",
                        "actual_pct": 0.0455893390113556,
                        "correct": true
                    },
                    "TSLA": {
                        "predicted_dir": "Down",
                        "predicted_pct": -0.004326254552818868,
                        "actual_dir": "Down",
                        "actual_pct": -0.020461618900717116,
                        "correct": true
                    },
                    "RKLB": {
                        "predicted_dir": "Up",
                        "predicted_pct": 0.026587195578010793,
                        "actual_dir": "Up",
                        "actual_pct": 0.03201764495321335,
                        "correct": true
                    },
                    "Bitcoin": {
                        "predicted_dir": "Down",
                        "predicted_pct": -0.0009640580793882476,
                        "actual_dir": "Down",
                        "actual_pct": -0.016291642540647827,
                        "correct": true
                    }
                }
            },
            {
                "for_date": "2026-06-19",
                "made_on": "2026-06-18",
                "symbols": {
                    "S&P 500": {
                        "predicted_dir": "Up",
                        "predicted_pct": 0.00041186391133402316,
                        "actual_dir": "Up",
                        "actual_pct": 0.010846212235623454,
                        "correct": true
                    },
                    "Nasdaq": {
                        "predicted_dir": "Down",
                        "predicted_pct": -0.002369006674989324,
                        "actual_dir": "Up",
                        "actual_pct": 0.01907147666194554,
                        "correct": false
                    },
                    "Gold": {
                        "predicted_dir": "Down",
                        "predicted_pct": -0.0020117504520551057,
                        "actual_dir": "Down",
                        "actual_pct": -0.03539879514198848,
                        "correct": true
                    },
                    "SCB": {
                        "predicted_dir": "Down",
                        "predicted_pct": -0.0017348727066412739,
                        "actual_dir": "Down",
                        "actual_pct": 0.0,
                        "correct": true
                    },
                    "TQM": {
                        "predicted_dir": "Up",
                        "predicted_pct": 0.0012032887594739645,
                        "actual_dir": "Up",
                        "actual_pct": 0.014814800686306424,
                        "correct": true
                    },
                    "IVV": {
                        "predicted_dir": "Down",
                        "predicted_pct": -0.004563030869095231,
                        "actual_dir": "Up",
                        "actual_pct": 0.010099514075951173,
                        "correct": false
                    },
                    "Google": {
                        "predicted_dir": "Down",
                        "predicted_pct": -0.0065083065972516485,
                        "actual_dir": "Up",
                        "actual_pct": 0.01165504861261585,
                        "correct": false
                    },
                    "NVDA": {
                        "predicted_dir": "Down",
                        "predicted_pct": -0.00442332276899301,
                        "actual_dir": "Up",
                        "actual_pct": 0.029513846689763496,
                        "correct": false
                    },
                    "AMD": {
                        "predicted_dir": "Up",
                        "predicted_pct": 0.004907795173365603,
                        "actual_dir": "Up",
                        "actual_pct": 0.04856777941973724,
                        "correct": true
                    },
                    "TSM": {
                        "predicted_dir": "Up",
                        "predicted_pct": 0.007406443547973584,
                        "actual_dir": "Up",
                        "actual_pct": 0.06935092362371299,
                        "correct": true
                    },
                    "SMH": {
                        "predicted_dir": "Up",
                        "predicted_pct": 0.002871744021354592,
                        "actual_dir": "Up",
                        "actual_pct": 0.05755090127049227,
                        "correct": true
                    },
                    "MU": {
                        "predicted_dir": "Up",
                        "predicted_pct": 0.002821848666153309,
                        "actual_dir": "Up",
                        "actual_pct": 0.08704076335870717,
                        "correct": true
                    },
                    "WDC": {
                        "predicted_dir": "Up",
                        "predicted_pct": 0.021146183724916515,
                        "actual_dir": "Up",
                        "actual_pct": 0.0478844808562012,
                        "correct": true
                    },
                    "TSLA": {
                        "predicted_dir": "Down",
                        "predicted_pct": -0.007643719896602735,
                        "actual_dir": "Up",
                        "actual_pct": 0.010368800900483349,
                        "correct": false
                    },
                    "RKLB": {
                        "predicted_dir": "Up",
                        "predicted_pct": 0.024243295675824436,
                        "actual_dir": "Down",
                        "actual_pct": -0.006853171607320064,
                        "correct": false
                    },
                    "Bitcoin": {
                        "predicted_dir": "Down",
                        "predicted_pct": -0.003992781888934149,
                        "actual_dir": "Down",
                        "actual_pct": -0.02476180820201318,
                        "correct": true
                    }
                }
            },
            {
                "for_date": "2026-06-20",
                "made_on": "2026-06-19",
                "symbols": {
                    "Gold": {
                        "predicted_dir": "Down",
                        "predicted_pct": -0.010575305912823421,
                        "actual_dir": "Down",
                        "actual_pct": -0.012120971124928721,
                        "correct": true
                    },
                    "SCB": {
                        "predicted_dir": "Down",
                        "predicted_pct": -0.0018366902370633058,
                        "actual_dir": "Down",
                        "actual_pct": -0.007042253521126761,
                        "correct": true
                    },
                    "TQM": {
                        "predicted_dir": "Down",
                        "predicted_pct": -0.00193872162262214,
                        "actual_dir": "Down",
                        "actual_pct": 0.0,
                        "correct": true
                    },
                    "IVV": {
                        "predicted_dir": "Up",
                        "predicted_pct": 0.003568576990999224,
                        "actual_dir": "Up",
                        "actual_pct": 0.010099514075951173,
                        "correct": true
                    },
                    "Google": {
                        "predicted_dir": "Up",
                        "predicted_pct": 0.0015547287396878709,
                        "actual_dir": "Up",
                        "actual_pct": 0.01165504861261585,
                        "correct": true
                    },
                    "NVDA": {
                        "predicted_dir": "Up",
                        "predicted_pct": 0.001627358782466351,
                        "actual_dir": "Up",
                        "actual_pct": 0.029513846689763496,
                        "correct": true
                    },
                    "AMD": {
                        "predicted_dir": "Up",
                        "predicted_pct": 0.012029389940652828,
                        "actual_dir": "Up",
                        "actual_pct": 0.04856777941973724,
                        "correct": true
                    },
                    "TSM": {
                        "predicted_dir": "Up",
                        "predicted_pct": 0.024608169542552235,
                        "actual_dir": "Up",
                        "actual_pct": 0.06935092362371299,
                        "correct": true
                    },
                    "SMH": {
                        "predicted_dir": "Up",
                        "predicted_pct": 0.021329424294246866,
                        "actual_dir": "Up",
                        "actual_pct": 0.05755090127049227,
                        "correct": true
                    },
                    "MU": {
                        "predicted_dir": "Up",
                        "predicted_pct": 0.028580499111668694,
                        "actual_dir": "Up",
                        "actual_pct": 0.08704076335870717,
                        "correct": true
                    },
                    "WDC": {
                        "predicted_dir": "Up",
                        "predicted_pct": 0.03473520712097243,
                        "actual_dir": "Up",
                        "actual_pct": 0.0478844808562012,
                        "correct": true
                    },
                    "TSLA": {
                        "predicted_dir": "Up",
                        "predicted_pct": 0.0024466415975903408,
                        "actual_dir": "Up",
                        "actual_pct": 0.010368800900483349,
                        "correct": true
                    },
                    "RKLB": {
                        "predicted_dir": "Down",
                        "predicted_pct": -0.018769563180181217,
                        "actual_dir": "Down",
                        "actual_pct": -0.006853171607320064,
                        "correct": true
                    },
                    "Bitcoin": {
                        "predicted_dir": "Down",
                        "predicted_pct": -0.013217368284301695,
                        "actual_dir": "Down",
                        "actual_pct": -0.013818344197562785,
                        "correct": true
                    }
                }
            },
            {
                "for_date": "2026-06-21",
                "made_on": "2026-06-20",
                "symbols": {
                    "Gold": {
                        "predicted_dir": "Down",
                        "predicted_pct": -0.0043194902480086506,
                        "actual_dir": "Down",
                        "actual_pct": -0.012120971124928721,
                        "correct": true
                    },
                    "SCB": {
                        "predicted_dir": "Down",
                        "predicted_pct": -0.0027611731163086546,
                        "actual_dir": "Down",
                        "actual_pct": -0.007042253521126761,
                        "correct": true
                    },
                    "TQM": {
                        "predicted_dir": "Up",
                        "predicted_pct": 0.00021293983152623924,
                        "actual_dir": "Down",
                        "actual_pct": 0.0,
                        "correct": false
                    },
                    "IVV": {
                        "predicted_dir": "Up",
                        "predicted_pct": 0.0044551236185793285,
                        "actual_dir": "Up",
                        "actual_pct": 0.010099514075951173,
                        "correct": true
                    },
                    "Google": {
                        "predicted_dir": "Up",
                        "predicted_pct": 0.0063916269143261,
                        "actual_dir": "Up",
                        "actual_pct": 0.01165504861261585,
                        "correct": true
                    },
                    "NVDA": {
                        "predicted_dir": "Up",
                        "predicted_pct": 0.004228752513622938,
                        "actual_dir": "Up",
                        "actual_pct": 0.029513846689763496,
                        "correct": true
                    },
                    "AMD": {
                        "predicted_dir": "Up",
                        "predicted_pct": 0.017765913943413213,
                        "actual_dir": "Up",
                        "actual_pct": 0.04856777941973724,
                        "correct": true
                    },
                    "TSM": {
                        "predicted_dir": "Up",
                        "predicted_pct": 0.03498270642289554,
                        "actual_dir": "Up",
                        "actual_pct": 0.06935092362371299,
                        "correct": true
                    },
                    "SMH": {
                        "predicted_dir": "Up",
                        "predicted_pct": 0.026017772461116587,
                        "actual_dir": "Up",
                        "actual_pct": 0.05755090127049227,
                        "correct": true
                    },
                    "MU": {
                        "predicted_dir": "Up",
                        "predicted_pct": 0.03755746415527758,
                        "actual_dir": "Up",
                        "actual_pct": 0.08704076335870717,
                        "correct": true
                    },
                    "WDC": {
                        "predicted_dir": "Up",
                        "predicted_pct": 0.03473519924162078,
                        "actual_dir": "Up",
                        "actual_pct": 0.0478844808562012,
                        "correct": true
                    },
                    "TSLA": {
                        "predicted_dir": "Up",
                        "predicted_pct": 0.003906582715664042,
                        "actual_dir": "Up",
                        "actual_pct": 0.010368800900483349,
                        "correct": true
                    },
                    "RKLB": {
                        "predicted_dir": "Down",
                        "predicted_pct": -0.018769563165873304,
                        "actual_dir": "Down",
                        "actual_pct": -0.006853171607320064,
                        "correct": true
                    },
                    "Bitcoin": {
                        "predicted_dir": "Down",
                        "predicted_pct": -0.0004955969071442192,
                        "actual_dir": "Up",
                        "actual_pct": 0.010840961404372459,
                        "correct": false
                    }
                }
            },
            {
                "for_date": "2026-06-22",
                "made_on": "2026-06-21",
                "symbols": {
                    "S&P 500": {
                        "predicted_dir": "Up",
                        "predicted_pct": 0.005632674946580353,
                        "actual_dir": "Up",
                        "actual_pct": 0.010846212235623454,
                        "correct": true
                    },
                    "Nasdaq": {
                        "predicted_dir": "Down",
                        "predicted_pct": -0.0004224087844745593,
                        "actual_dir": "Up",
                        "actual_pct": 0.01907140160428249,
                        "correct": false
                    },
                    "Gold": {
                        "predicted_dir": "Down",
                        "predicted_pct": -0.0044121763760536364,
                        "actual_dir": "Down",
                        "actual_pct": -0.016547880194064078,
                        "correct": true
                    },
                    "SCB": {
                        "predicted_dir": "Down",
                        "predicted_pct": -0.0026047288392455187,
                        "actual_dir": "Down",
                        "actual_pct": -0.007042253521126761,
                        "correct": true
                    },
                    "TQM": {
                        "predicted_dir": "Down",
                        "predicted_pct": -0.00021947962551625714,
                        "actual_dir": "Down",
                        "actual_pct": 0.0,
                        "correct": true
                    },
                    "IVV": {
                        "predicted_dir": "Up",
                        "predicted_pct": 0.004803340744623397,
                        "actual_dir": "Up",
                        "actual_pct": 0.010099514075951173,
                        "correct": true
                    },
                    "Google": {
                        "predicted_dir": "Up",
                        "predicted_pct": 0.0072445002019105136,
                        "actual_dir": "Up",
                        "actual_pct": 0.01165504861261585,
                        "correct": true
                    },
                    "NVDA": {
                        "predicted_dir": "Up",
                        "predicted_pct": 0.0061711845370091105,
                        "actual_dir": "Up",
                        "actual_pct": 0.029513846689763496,
                        "correct": true
                    },
                    "AMD": {
                        "predicted_dir": "Up",
                        "predicted_pct": 0.018293553084902495,
                        "actual_dir": "Up",
                        "actual_pct": 0.04856777941973724,
                        "correct": true
                    },
                    "TSM": {
                        "predicted_dir": "Up",
                        "predicted_pct": 0.037499931190826806,
                        "actual_dir": "Up",
                        "actual_pct": 0.06935092362371299,
                        "correct": true
                    },
                    "SMH": {
                        "predicted_dir": "Up",
                        "predicted_pct": 0.02892565670568774,
                        "actual_dir": "Up",
                        "actual_pct": 0.05755090127049227,
                        "correct": true
                    },
                    "MU": {
                        "predicted_dir": "Up",
                        "predicted_pct": 0.02772239891035497,
                        "actual_dir": "Up",
                        "actual_pct": 0.08704076335870717,
                        "correct": true
                    },
                    "WDC": {
                        "predicted_dir": "Up",
                        "predicted_pct": 0.034735207821951566,
                        "actual_dir": "Up",
                        "actual_pct": 0.0478844808562012,
                        "correct": true
                    },
                    "TSLA": {
                        "predicted_dir": "Up",
                        "predicted_pct": 0.0016974436278892131,
                        "actual_dir": "Up",
                        "actual_pct": 0.010368800900483349,
                        "correct": true
                    },
                    "RKLB": {
                        "predicted_dir": "Down",
                        "predicted_pct": -0.018769563180181217,
                        "actual_dir": "Down",
                        "actual_pct": -0.006853171607320064,
                        "correct": true
                    },
                    "Bitcoin": {
                        "predicted_dir": "Up",
                        "predicted_pct": 0.0009949670538931996,
                        "actual_dir": "Down",
                        "actual_pct": -0.013444280960273468,
                        "correct": false
                    }
                }
            }
        ]
    },
    "news": [
        {
            "title": "Stocks Sink in Broad AI Rout Sparked by China's DeepSeek",
            "domain": "wsj.com",
            "credibility": 95
        },
        {
            "title": "Comex Gold, Silver Settle Lower",
            "domain": "wsj.com",
            "credibility": 95
        },
        {
            "title": "DeepSeek Won't Sink U.S. AI Titans",
            "domain": "wsj.com",
            "credibility": 95
        },
        {
            "title": "Financial Services Roundup: Market Talk",
            "domain": "wsj.com",
            "credibility": 95
        },
        {
            "title": "Arabica Coffee Prices Hit Record on U.S., Colombia Tariff Spat",
            "domain": "wsj.com",
            "credibility": 95
        },
        {
            "title": "Swiss franc, Japanese yen Rise as DeepSeek News Boosts Safe Havens",
            "domain": "wsj.com",
            "credibility": 95
        },
        {
            "title": "Natural Gas Falls on Shifting Weather Forecasts",
            "domain": "wsj.com",
            "credibility": 95
        },
        {
            "title": "Building-Products Distributor QXO Launches Hostile Bid for Beacon",
            "domain": "wsj.com",
            "credibility": 95
        },
        {
            "title": "Natural-Gas Firm Diversified Energy Strikes Deal for Permian Basin Player",
            "domain": "wsj.com",
            "credibility": 95
        },
        {
            "title": "What's New This Tax Season That Can Save You Money",
            "domain": "wsj.com",
            "credibility": 95
        },
        {
            "title": "Chinese Investors With Few Options Turn to Dividends",
            "domain": "wsj.com",
            "credibility": 95
        },
        {
            "title": "U.S. Treasury Yields Fall But Direction for Long-End Yields Still Seen Upward",
            "domain": "wsj.com",
            "credibility": 95
        },
        {
            "title": "Russia's Crude Exports Fairly Stable Despite U.S. Sanctions, Goldman Says",
            "domain": "wsj.com",
            "credibility": 95
        },
        {
            "title": "The Extra Reward for Owning Stocks Over Bonds Has Disappeared",
            "domain": "wsj.com",
            "credibility": 95
        },
        {
            "title": "Heard on the Street's Stock-Picking Series",
            "domain": "wsj.com",
            "credibility": 95
        },
        {
            "title": "'Regime change but in a velvet glove': How Kevin Warsh has set out to remake the Fed",
            "domain": "cnbc.com",
            "credibility": 92
        },
        {
            "title": "U.S. and Iran begin peace talks amid conflicting claims over Strait of Hormuz",
            "domain": "cnbc.com",
            "credibility": 92
        },
        {
            "title": "Bitcoin's future as revolutionary as the smartphone, according to CoinDesk",
            "domain": "cnbc.com",
            "credibility": 92
        },
        {
            "title": "The riskiest SpaceX stock trade of all had a big first week",
            "domain": "cnbc.com",
            "credibility": 92
        },
        {
            "title": "The average SpaceX buyer post-IPO is almost under water after two-day slide",
            "domain": "cnbc.com",
            "credibility": 92
        },
        {
            "title": "Markets are set for a much more hawkish Warsh Fed than expected",
            "domain": "cnbc.com",
            "credibility": 92
        },
        {
            "title": "Stocks making the biggest moves premarket: Intel, SpaceX, Micron, Carnival & more",
            "domain": "cnbc.com",
            "credibility": 92
        },
        {
            "title": "Jeffrey Gundlach says Fed's Warsh is not going to be the 'easy money' chairman many hoped for",
            "domain": "cnbc.com",
            "credibility": 92
        },
        {
            "title": "Chairman Warsh abstains from giving rate forecast as several members signal a hike in 2026",
            "domain": "cnbc.com",
            "credibility": 92
        },
        {
            "title": "Chairman Warsh drastically alters Fed rate statement. Here's what's changed",
            "domain": "cnbc.com",
            "credibility": 92
        }
    ],
    "news_fetch_stats": {
        "total_fetched": 40,
        "accepted": 40,
        "rejected": 0,
        "min_credibility": 90
    }
}